quart_dishka/__init__.py
quart_dishka/container.py
quart_dishka/exceptions.py
quart_dishka/extension.py
quart_dishka/provider.py
quart_dishka/py.typed
quart_dishka-1.0.0.dist-info/licenses/LICENSE
quart_dishka-1.0.0.dist-info/METADATA
quart_dishka-1.0.0.dist-info/WHEEL
quart_dishka-1.0.0.dist-info/top_level.txt
quart_dishka-1.0.0.dist-info/RECORD
