Metadata-Version: 2.4
Name: quart-dishka
Version: 1.0.0
Summary: Quart integration for dishka
Author-email: Andrew Hrimov <andrew.hrimov@gmail.com>
License-Expression: Apache-2.0
Project-URL: Source, https://github.com/hrimov/quart-dishka
Project-URL: Homepage, https://github.com/hrimov/quart-dishka
Project-URL: Documentation, https://github.com/hrimov/quart-dishka
Project-URL: Bug Tracker, https://github.com/hrimov/quart-dishka/issues
Classifier: Programming Language :: Python :: 3.10
Classifier: Programming Language :: Python :: 3.11
Classifier: Programming Language :: Python :: 3.12
Classifier: Typing :: Typed
Requires-Python: >=3.10
License-File: LICENSE
Requires-Dist: dishka>=1.4.0
Requires-Dist: quart>=0.20.0
Requires-Dist: typing_extensions; python_version < "3.11"
Provides-Extra: lint
Requires-Dist: ruff; extra == "lint"
Requires-Dist: mypy; extra == "lint"
Provides-Extra: test
Requires-Dist: nox; extra == "test"
Dynamic: license-file
